SplineSmooth3D/SplineSmooth3D.py
SplineSmooth3D/SplineSupport.py
SplineSmooth3D/__init__.py
SplineSmooth3D-0.1.2.data/scripts/measureprofile.py
SplineSmooth3D-0.1.2.data/scripts/splinesmooth3d-demo.py
SplineSmooth3D-0.1.2.data/scripts/splinesmooth3d-j0-demo.py
SplineSmooth3D-0.1.2.data/scripts/splinesmooth3d-promote-demo.py
SplineSmooth3D-0.1.2.data/scripts/splinesmooth3d-zerounsupported-demo.py
SplineSmooth3D-0.1.2.data/scripts/test-scipyspline-demo.py
SplineSmooth3D-0.1.2.dist-info/LICENSE.txt
SplineSmooth3D-0.1.2.dist-info/METADATA
SplineSmooth3D-0.1.2.dist-info/WHEEL
SplineSmooth3D-0.1.2.dist-info/top_level.txt
SplineSmooth3D-0.1.2.dist-info/RECORD
